bible_api/__init__.py
bible_api/analysis.py
bible_api/data.py
bible_api/query.py
bible_api/quiz.py
bible_api-0.1.0.dist-info/METADATA
bible_api-0.1.0.dist-info/WHEEL
bible_api-0.1.0.dist-info/entry_points.txt
bible_api-0.1.0.dist-info/top_level.txt
bible_api-0.1.0.dist-info/RECORD
