Metadata-Version: 2.1
Name: bible-api
Version: 0.1.0
Summary: A Python package for querying and analyzing the Bible dataset
Home-page: https://github.com/isaiaholad/bible_api
Author: isaiaholad
Author-email: isaiaholad@gmail.com
Classifier: Programming Language :: Python :: 3
Classifier: License :: OSI Approved :: MIT License
Classifier: Operating System :: OS Independent
Requires-Python: >=3.6
Requires-Dist: pandas
Requires-Dist: wordcloud
